LICENSE
MANIFEST.in
Makefile
README.rst
requirements.txt
setup.py
mutagenwrapper/__init__.py
mutagenwrapper/_flac.py
mutagenwrapper/_handlers.py
mutagenwrapper/_mp3.py
mutagenwrapper/_mp4.py
mutagenwrapper/_util.py
mutagenwrapper/_wrappers.py
mutagenwrapper/exceptions.py
mutagenwrapper/version.py
mutagenwrapper.egg-info/PKG-INFO
mutagenwrapper.egg-info/SOURCES.txt
mutagenwrapper.egg-info/dependency_links.txt
mutagenwrapper.egg-info/requires.txt
mutagenwrapper.egg-info/top_level.txt
tests/test_mutagenwrapper.py
tests/data/conflict.m4a
tests/data/conflict.mp3
tests/data/cover.jpg
tests/data/multiframe.m4a
tests/data/multiframe.mp3
tests/data/silence.flac
tests/data/silence.m4a
tests/data/silence.mp3