Metadata-Version: 1.1
Name: mutagenwrapper
Version: 0.0.5
Summary: wrapper for mutagen that normalizes tags between various audio file formats
Home-page: https://github.com/clee704/mutagenwrapper
Author: Choongmin Lee
Author-email: choongmin@me.com
License: MIT License
Keywords: audio metadata tags
Platform: UNKNOWN
Classifier: Development Status :: 2 - Pre-Alpha
Classifier: Intended Audience :: Developers
Classifier: Intended Audience :: End Users/Desktop
Classifier: License :: OSI Approved :: MIT License
Classifier: Programming Language :: Python
Classifier: Topic :: Multimedia :: Sound/Audio
Classifier: Topic :: Utilities
